fastapi_crudrouter_v2/__init__.py
fastapi_crudrouter_v2/_version.py
fastapi_crudrouter_v2/core/__init__.py
fastapi_crudrouter_v2/core/_base.py
fastapi_crudrouter_v2/core/_router.py
fastapi_crudrouter_v2/core/_types.py
fastapi_crudrouter_v2/core/_utils.py
fastapi_crudrouter_v2/py.typed
fastapi_crudrouter_v2-0.1.2.dist-info/METADATA
fastapi_crudrouter_v2-0.1.2.dist-info/WHEEL
fastapi_crudrouter_v2-0.1.2.dist-info/licenses/LICENSE
fastapi_crudrouter_v2-0.1.2.dist-info/RECORD
