Metadata-Version: 2.4
Name: fastapi-crudrouter-v2
Version: 0.1.2
Summary: A dynamic FastAPI router that automatically creates CRUD routes for your models
License-File: LICENSE
Author: pasha_danilevich
Author-email: danilevitch.pasha@yandex.ru
Requires-Python: >=3.9,<4.0
Classifier: Programming Language :: Python :: 3
Classifier: Programming Language :: Python :: 3.9
Classifier: Programming Language :: Python :: 3.10
Classifier: Programming Language :: Python :: 3.11
Classifier: Programming Language :: Python :: 3.12
Classifier: Programming Language :: Python :: 3.13
Classifier: Programming Language :: Python :: 3.14
